{
  "response": [
    {
      "maintainer": "Achille (0xSharkBoy)",
      "oem": "Samsung",
      "device": "Galaxy Note 10 Plus 5G",
      "filename": "EvolutionX-15.0-20250119-d2x-10.2-Official.zip",
      "download": "https://sourceforge.net/projects/evolution-x/files/d2x/15/EvolutionX-15.0-20250119-d2x-10.2-Official.zip/download",
      "timestamp": 1737305464,
      "md5": "824b242a882471c7eb99d21edea6abc2",
      "sha256": "8c11251093fa59a7a6ad57f7891a854a2d4b5ec905644c6e504215949c046c22",
      "size": 2421888341,
      "version": "10.2",
      "buildtype": "Monthly",
      "forum": "https://xdaforums.com/t/rom-official-15-evolutionx-10-x-aosp-encryption.4669086/",
      "firmware": "",
      "paypal": "https://ko-fi.com/0xsharkboy",
      "telegram": "https://t.me/EvolutionXexynos982x",
      "github": "0xsharkboy",
      "initial_installation_images": [
        "recovery"
      ]
    }
  ]
}
